{"playerId":"robot1","positionX":0,"positionZ":0,"energy":200,"maxEnergy":200,"accumulator":0,"maxAccumulator":1000,"totalPedometerEnergy":0,"learningPoints":4980,"maxLearningPoints":5000,"level":1,"xp":0,"skillPoints":0,"storyStep":0,"seenDialogues":[],"hasSeenIntro":true,"lastUpdate":1769159495984,"skills":{"S":{"investedEnergy":0,"level":0},"P":{"investedEnergy":0,"level":0},"E":{"investedEnergy":0,"level":0},"C":{"investedEnergy":0,"level":0},"I":{"investedEnergy":0,"level":0},"A":{"investedEnergy":0,"level":0},"L":{"investedEnergy":0,"level":0}},"inventory":{},"kodex":{},"quests":{"active":[{"questId":"quest_where_am_i","questTitle":"Kde to som","questType":"main","status":"active","startedAt":"2026-01-23T09:13:26.217Z","objectivesProgress":{"0":{"completed":false,"progress":0,"target":1},"1":{"completed":false,"progress":0,"target":1}},"completedAt":null}],"completed":[]},"currentXP":50,"xpToNextLevel":100}